{
        "metadata": {
                "x_col": "reductionInCases",
                "y_col": "cost",
                "id_col": "intervention",
                "format": "long"
        },
        "series": [
            {
                "id": "none",
                "name": "No intervention",
                "type": "scatter",
                "marker": {"color": "grey", "size": 10},
                "error_x": {
                    "type": "data",
                    "width": 0,
                    "col": "reductionInCasesErrorPlus",
                    "colminus": "reductionInCasesErrorMinus"
                }
            },
            {
                "id": "ITN",
                "name": "Pyrethoid ITN",
                "type": "scatter",
                "marker": {"color": "blue", "size": 10},
                "error_x": {
                    "type": "data",
                    "width": 0,
                    "col": "reductionInCasesErrorPlus",
                    "colminus": "reductionInCasesErrorMinus"
                }
            },
            {
                "id": "PBO",
                "name": "Switch to Pyrethoid-PBO ITN",
                "type": "scatter",
                "marker": {"color": "turquoise", "size": 10},
                "error_x": {
                    "type": "data",
                    "width": 0,
                    "col": "reductionInCasesErrorPlus",
                    "colminus": "reductionInCasesErrorMinus"
                }
            },
            {
                "id": "IRS",
                "name": "Only IRS",
                "type": "scatter",
                "marker": {"color": "purple", "size": 10},
                "error_x": {
                    "type": "data",
                    "width": 0,
                    "col": "reductionInCasesErrorPlus",
                    "colminus": "reductionInCasesErrorMinus"
                }
            },
            {
                "id": "ITN-IRS",
                "name": "Add IRS to Pyrethoid ITN",
                "type": "scatter",
                "marker": {"color": "darkred", "size": 10},
                "error_x": {
                    "type": "data",
                    "width": 0,
                    "col": "reductionInCasesErrorPlus",
                    "colminus": "reductionInCasesErrorMinus"
                }
            },
            {
                "id": "PBO-IRS",
                "name": "Add IRS to Pyrethoid-PBO ITN",
                "type": "scatter",
                "marker": {"color": "orange", "size": 10},
                "error_x": {
                    "type": "data",
                    "width": 0,
                    "col": "reductionInCasesErrorPlus",
                    "colminus": "reductionInCasesErrorMinus"
                }
            }
        ],
        "layout": {
            "title": "Strategy costs over 3 years vs Efficacy",
            "xaxis": {
                "title": "Efficacy against cases (%)",
                "showline": true,
                "range": [-2, 100],
                "tickvals": [0, 20, 40, 60, 80, 100],
                "autorange": false,
                "zeroline": false
            },
            "yaxis": {
                "title": "Total costs ($10,000 USD)",
                "showline": true,
                "range": [-2, 30],
                "tickvals": [0, 10 , 20],
                "autorange": false,
                "zeroline": false
        },
        "hoverlabel": {
            "namelength": -1
        },
        "mintcustom": {
            "hoverposition": "below"
        },
        "hovermode": "closest"
    }
}
